
<annotation>
	<folder>annotations</folder>
	<filename>9999972_00000_d_0000097.jpg</filename>
	<path>/content/datasets/VisDrone/VisDrone2019-DET-train/images/9999972_00000_d_0000097.jpg</path>
	<source>
		<database>Unknown</database>
	</source>
	<size>
		<width>1078</width>
		<height>1916</height>
		<depth>3</depth>
	</size>
	<segmented>0</segmented>
	<object>
		<name>Car</name>
		<pose>Unspecified</pose>
		<truncated>0</truncated>
		<difficult>0</difficult>
		<bndbox>
			<xmin>1513</xmin>
			<ymin>635</ymin>
			<xmax>1646</xmax>
			<ymax>731</ymax>
		</bndbox>
	</object>
	
	<object>
		<name>Car</name>
		<pose>Unspecified</pose>
		<truncated>0</truncated>
		<difficult>0</difficult>
		<bndbox>
			<xmin>1298</xmin>
			<ymin>602</ymin>
			<xmax>1357</xmax>
			<ymax>730</ymax>
		</bndbox>
	</object>
	
	<object>
		<name>Car</name>
		<pose>Unspecified</pose>
		<truncated>0</truncated>
		<difficult>0</difficult>
		<bndbox>
			<xmin>1069</xmin>
			<ymin>585</ymin>
			<xmax>1126</xmax>
			<ymax>707</ymax>
		</bndbox>
	</object>
	
	<object>
		<name>Car</name>
		<pose>Unspecified</pose>
		<truncated>0</truncated>
		<difficult>0</difficult>
		<bndbox>
			<xmin>932</xmin>
			<ymin>571</ymin>
			<xmax>988</xmax>
			<ymax>694</ymax>
		</bndbox>
	</object>
	
	<object>
		<name>Awning-tricycle</name>
		<pose>Unspecified</pose>
		<truncated>0</truncated>
		<difficult>0</difficult>
		<bndbox>
			<xmin>35</xmin>
			<ymin>319</ymin>
			<xmax>93</xmax>
			<ymax>394</ymax>
		</bndbox>
	</object>
	</annotation>