
<annotation>
	<folder>annotations</folder>
	<filename>9999945_00000_d_0000169.jpg</filename>
	<path>/content/datasets/VisDrone/VisDrone2019-DET-train/images/9999945_00000_d_0000169.jpg</path>
	<source>
		<database>Unknown</database>
	</source>
	<size>
		<width>1050</width>
		<height>1400</height>
		<depth>3</depth>
	</size>
	<segmented>0</segmented>
	<object>
		<name>Car</name>
		<pose>Unspecified</pose>
		<truncated>0</truncated>
		<difficult>0</difficult>
		<bndbox>
			<xmin>277</xmin>
			<ymin>572</ymin>
			<xmax>363</xmax>
			<ymax>613</ymax>
		</bndbox>
	</object>
	
	<object>
		<name>Car</name>
		<pose>Unspecified</pose>
		<truncated>0</truncated>
		<difficult>0</difficult>
		<bndbox>
			<xmin>243</xmin>
			<ymin>767</ymin>
			<xmax>386</xmax>
			<ymax>851</ymax>
		</bndbox>
	</object>
	
	<object>
		<name>Car</name>
		<pose>Unspecified</pose>
		<truncated>0</truncated>
		<difficult>0</difficult>
		<bndbox>
			<xmin>525</xmin>
			<ymin>853</ymin>
			<xmax>660</xmax>
			<ymax>941</ymax>
		</bndbox>
	</object>
	
	<object>
		<name>Car</name>
		<pose>Unspecified</pose>
		<truncated>0</truncated>
		<difficult>0</difficult>
		<bndbox>
			<xmin>696</xmin>
			<ymin>904</ymin>
			<xmax>835</xmax>
			<ymax>996</ymax>
		</bndbox>
	</object>
	
	<object>
		<name>Pedestrian</name>
		<pose>Unspecified</pose>
		<truncated>0</truncated>
		<difficult>0</difficult>
		<bndbox>
			<xmin>925</xmin>
			<ymin>218</ymin>
			<xmax>930</xmax>
			<ymax>237</ymax>
		</bndbox>
	</object>
	
	<object>
		<name>Pedestrian</name>
		<pose>Unspecified</pose>
		<truncated>0</truncated>
		<difficult>0</difficult>
		<bndbox>
			<xmin>931</xmin>
			<ymin>218</ymin>
			<xmax>938</xmax>
			<ymax>235</ymax>
		</bndbox>
	</object>
	
	<object>
		<name>Car</name>
		<pose>Unspecified</pose>
		<truncated>0</truncated>
		<difficult>0</difficult>
		<bndbox>
			<xmin>827</xmin>
			<ymin>838</ymin>
			<xmax>990</xmax>
			<ymax>923</ymax>
		</bndbox>
	</object>
	
	<object>
		<name>Car</name>
		<pose>Unspecified</pose>
		<truncated>0</truncated>
		<difficult>0</difficult>
		<bndbox>
			<xmin>900</xmin>
			<ymin>966</ymin>
			<xmax>1043</xmax>
			<ymax>1050</ymax>
		</bndbox>
	</object>
	
	<object>
		<name>Car</name>
		<pose>Unspecified</pose>
		<truncated>0</truncated>
		<difficult>0</difficult>
		<bndbox>
			<xmin>1228</xmin>
			<ymin>958</ymin>
			<xmax>1400</xmax>
			<ymax>1049</ymax>
		</bndbox>
	</object>
	</annotation>