
<annotation>
	<folder>annotations</folder>
	<filename>9999998_00259_d_0000213.jpg</filename>
	<path>/content/datasets/VisDrone/VisDrone2019-DET-train/images/9999998_00259_d_0000213.jpg</path>
	<source>
		<database>Unknown</database>
	</source>
	<size>
		<width>1500</width>
		<height>2000</height>
		<depth>3</depth>
	</size>
	<segmented>0</segmented>
	<object>
		<name>Car</name>
		<pose>Unspecified</pose>
		<truncated>0</truncated>
		<difficult>0</difficult>
		<bndbox>
			<xmin>0</xmin>
			<ymin>939</ymin>
			<xmax>112</xmax>
			<ymax>1089</ymax>
		</bndbox>
	</object>
	
	<object>
		<name>Car</name>
		<pose>Unspecified</pose>
		<truncated>0</truncated>
		<difficult>0</difficult>
		<bndbox>
			<xmin>16</xmin>
			<ymin>587</ymin>
			<xmax>291</xmax>
			<ymax>718</ymax>
		</bndbox>
	</object>
	
	<object>
		<name>Car</name>
		<pose>Unspecified</pose>
		<truncated>0</truncated>
		<difficult>0</difficult>
		<bndbox>
			<xmin>118</xmin>
			<ymin>162</ymin>
			<xmax>322</xmax>
			<ymax>245</ymax>
		</bndbox>
	</object>
	
	<object>
		<name>Car</name>
		<pose>Unspecified</pose>
		<truncated>0</truncated>
		<difficult>0</difficult>
		<bndbox>
			<xmin>1106</xmin>
			<ymin>929</ymin>
			<xmax>1400</xmax>
			<ymax>1093</ymax>
		</bndbox>
	</object>
	
	<object>
		<name>Car</name>
		<pose>Unspecified</pose>
		<truncated>0</truncated>
		<difficult>0</difficult>
		<bndbox>
			<xmin>977</xmin>
			<ymin>287</ymin>
			<xmax>1195</xmax>
			<ymax>391</ymax>
		</bndbox>
	</object>
	
	<object>
		<name>Car</name>
		<pose>Unspecified</pose>
		<truncated>0</truncated>
		<difficult>0</difficult>
		<bndbox>
			<xmin>687</xmin>
			<ymin>346</ymin>
			<xmax>895</xmax>
			<ymax>443</ymax>
		</bndbox>
	</object>
	
	<object>
		<name>People</name>
		<pose>Unspecified</pose>
		<truncated>0</truncated>
		<difficult>0</difficult>
		<bndbox>
			<xmin>781</xmin>
			<ymin>1010</ymin>
			<xmax>834</xmax>
			<ymax>1077</ymax>
		</bndbox>
	</object>
	
	<object>
		<name>Bicycle</name>
		<pose>Unspecified</pose>
		<truncated>0</truncated>
		<difficult>0</difficult>
		<bndbox>
			<xmin>759</xmin>
			<ymin>1028</ymin>
			<xmax>870</xmax>
			<ymax>1085</ymax>
		</bndbox>
	</object>
	
	<object>
		<name>People</name>
		<pose>Unspecified</pose>
		<truncated>0</truncated>
		<difficult>0</difficult>
		<bndbox>
			<xmin>1536</xmin>
			<ymin>326</ymin>
			<xmax>1578</xmax>
			<ymax>399</ymax>
		</bndbox>
	</object>
	
	<object>
		<name>Motor</name>
		<pose>Unspecified</pose>
		<truncated>0</truncated>
		<difficult>0</difficult>
		<bndbox>
			<xmin>1508</xmin>
			<ymin>338</ymin>
			<xmax>1595</xmax>
			<ymax>386</ymax>
		</bndbox>
	</object>
	
	<object>
		<name>Bicycle</name>
		<pose>Unspecified</pose>
		<truncated>0</truncated>
		<difficult>0</difficult>
		<bndbox>
			<xmin>1770</xmin>
			<ymin>357</ymin>
			<xmax>1833</xmax>
			<ymax>409</ymax>
		</bndbox>
	</object>
	
	<object>
		<name>People</name>
		<pose>Unspecified</pose>
		<truncated>0</truncated>
		<difficult>0</difficult>
		<bndbox>
			<xmin>1797</xmin>
			<ymin>333</ymin>
			<xmax>1838</xmax>
			<ymax>392</ymax>
		</bndbox>
	</object>
	</annotation>