
<annotation>
	<folder>annotations</folder>
	<filename>9999955_00000_d_0000013.jpg</filename>
	<path>/content/datasets/VisDrone/VisDrone2019-DET-train/images/9999955_00000_d_0000013.jpg</path>
	<source>
		<database>Unknown</database>
	</source>
	<size>
		<width>788</width>
		<height>1400</height>
		<depth>3</depth>
	</size>
	<segmented>0</segmented>
	<object>
		<name>Van</name>
		<pose>Unspecified</pose>
		<truncated>0</truncated>
		<difficult>0</difficult>
		<bndbox>
			<xmin>530</xmin>
			<ymin>210</ymin>
			<xmax>545</xmax>
			<ymax>226</ymax>
		</bndbox>
	</object>
	
	<object>
		<name>Car</name>
		<pose>Unspecified</pose>
		<truncated>0</truncated>
		<difficult>0</difficult>
		<bndbox>
			<xmin>544</xmin>
			<ymin>225</ymin>
			<xmax>559</xmax>
			<ymax>238</ymax>
		</bndbox>
	</object>
	
	<object>
		<name>Truck</name>
		<pose>Unspecified</pose>
		<truncated>0</truncated>
		<difficult>0</difficult>
		<bndbox>
			<xmin>616</xmin>
			<ymin>265</ymin>
			<xmax>630</xmax>
			<ymax>294</ymax>
		</bndbox>
	</object>
	
	<object>
		<name>Car</name>
		<pose>Unspecified</pose>
		<truncated>0</truncated>
		<difficult>0</difficult>
		<bndbox>
			<xmin>616</xmin>
			<ymin>296</ymin>
			<xmax>627</xmax>
			<ymax>314</ymax>
		</bndbox>
	</object>
	
	<object>
		<name>Car</name>
		<pose>Unspecified</pose>
		<truncated>0</truncated>
		<difficult>0</difficult>
		<bndbox>
			<xmin>612</xmin>
			<ymin>342</ymin>
			<xmax>628</xmax>
			<ymax>370</ymax>
		</bndbox>
	</object>
	
	<object>
		<name>Truck</name>
		<pose>Unspecified</pose>
		<truncated>0</truncated>
		<difficult>0</difficult>
		<bndbox>
			<xmin>578</xmin>
			<ymin>436</ymin>
			<xmax>595</xmax>
			<ymax>474</ymax>
		</bndbox>
	</object>
	
	<object>
		<name>Car</name>
		<pose>Unspecified</pose>
		<truncated>0</truncated>
		<difficult>0</difficult>
		<bndbox>
			<xmin>609</xmin>
			<ymin>442</ymin>
			<xmax>627</xmax>
			<ymax>471</ymax>
		</bndbox>
	</object>
	
	<object>
		<name>Van</name>
		<pose>Unspecified</pose>
		<truncated>0</truncated>
		<difficult>0</difficult>
		<bndbox>
			<xmin>1107</xmin>
			<ymin>130</ymin>
			<xmax>1135</xmax>
			<ymax>145</ymax>
		</bndbox>
	</object>
	
	<object>
		<name>Van</name>
		<pose>Unspecified</pose>
		<truncated>0</truncated>
		<difficult>0</difficult>
		<bndbox>
			<xmin>1207</xmin>
			<ymin>280</ymin>
			<xmax>1234</xmax>
			<ymax>309</ymax>
		</bndbox>
	</object>
	</annotation>