
<annotation>
	<folder>annotations</folder>
	<filename>9999951_00000_d_0000333.jpg</filename>
	<path>/content/datasets/VisDrone/VisDrone2019-DET-train/images/9999951_00000_d_0000333.jpg</path>
	<source>
		<database>Unknown</database>
	</source>
	<size>
		<width>788</width>
		<height>1400</height>
		<depth>3</depth>
	</size>
	<segmented>0</segmented>
	<object>
		<name>Car</name>
		<pose>Unspecified</pose>
		<truncated>0</truncated>
		<difficult>0</difficult>
		<bndbox>
			<xmin>1147</xmin>
			<ymin>80</ymin>
			<xmax>1208</xmax>
			<ymax>143</ymax>
		</bndbox>
	</object>
	
	<object>
		<name>Car</name>
		<pose>Unspecified</pose>
		<truncated>0</truncated>
		<difficult>0</difficult>
		<bndbox>
			<xmin>1338</xmin>
			<ymin>490</ymin>
			<xmax>1400</xmax>
			<ymax>606</ymax>
		</bndbox>
	</object>
	
	<object>
		<name>Car</name>
		<pose>Unspecified</pose>
		<truncated>0</truncated>
		<difficult>0</difficult>
		<bndbox>
			<xmin>249</xmin>
			<ymin>58</ymin>
			<xmax>332</xmax>
			<ymax>100</ymax>
		</bndbox>
	</object>
	
	<object>
		<name>Pedestrian</name>
		<pose>Unspecified</pose>
		<truncated>0</truncated>
		<difficult>0</difficult>
		<bndbox>
			<xmin>1055</xmin>
			<ymin>314</ymin>
			<xmax>1066</xmax>
			<ymax>345</ymax>
		</bndbox>
	</object>
	
	<object>
		<name>Pedestrian</name>
		<pose>Unspecified</pose>
		<truncated>0</truncated>
		<difficult>0</difficult>
		<bndbox>
			<xmin>1068</xmin>
			<ymin>321</ymin>
			<xmax>1084</xmax>
			<ymax>346</ymax>
		</bndbox>
	</object>
	
	<object>
		<name>Pedestrian</name>
		<pose>Unspecified</pose>
		<truncated>0</truncated>
		<difficult>0</difficult>
		<bndbox>
			<xmin>962</xmin>
			<ymin>304</ymin>
			<xmax>979</xmax>
			<ymax>329</ymax>
		</bndbox>
	</object>
	
	<object>
		<name>Pedestrian</name>
		<pose>Unspecified</pose>
		<truncated>0</truncated>
		<difficult>0</difficult>
		<bndbox>
			<xmin>974</xmin>
			<ymin>84</ymin>
			<xmax>985</xmax>
			<ymax>106</ymax>
		</bndbox>
	</object>
	
	<object>
		<name>Pedestrian</name>
		<pose>Unspecified</pose>
		<truncated>0</truncated>
		<difficult>0</difficult>
		<bndbox>
			<xmin>1039</xmin>
			<ymin>116</ymin>
			<xmax>1048</xmax>
			<ymax>143</ymax>
		</bndbox>
	</object>
	
	<object>
		<name>Pedestrian</name>
		<pose>Unspecified</pose>
		<truncated>0</truncated>
		<difficult>0</difficult>
		<bndbox>
			<xmin>1048</xmin>
			<ymin>118</ymin>
			<xmax>1057</xmax>
			<ymax>145</ymax>
		</bndbox>
	</object>
	
	<object>
		<name>Pedestrian</name>
		<pose>Unspecified</pose>
		<truncated>0</truncated>
		<difficult>0</difficult>
		<bndbox>
			<xmin>1059</xmin>
			<ymin>120</ymin>
			<xmax>1066</xmax>
			<ymax>148</ymax>
		</bndbox>
	</object>
	
	<object>
		<name>People</name>
		<pose>Unspecified</pose>
		<truncated>0</truncated>
		<difficult>0</difficult>
		<bndbox>
			<xmin>954</xmin>
			<ymin>80</ymin>
			<xmax>965</xmax>
			<ymax>92</ymax>
		</bndbox>
	</object>
	
	<object>
		<name>People</name>
		<pose>Unspecified</pose>
		<truncated>0</truncated>
		<difficult>0</difficult>
		<bndbox>
			<xmin>940</xmin>
			<ymin>77</ymin>
			<xmax>952</xmax>
			<ymax>92</ymax>
		</bndbox>
	</object>
	
	<object>
		<name>People</name>
		<pose>Unspecified</pose>
		<truncated>0</truncated>
		<difficult>0</difficult>
		<bndbox>
			<xmin>929</xmin>
			<ymin>79</ymin>
			<xmax>939</xmax>
			<ymax>95</ymax>
		</bndbox>
	</object>
	
	<object>
		<name>People</name>
		<pose>Unspecified</pose>
		<truncated>0</truncated>
		<difficult>0</difficult>
		<bndbox>
			<xmin>874</xmin>
			<ymin>78</ymin>
			<xmax>883</xmax>
			<ymax>95</ymax>
		</bndbox>
	</object>
	
	<object>
		<name>People</name>
		<pose>Unspecified</pose>
		<truncated>0</truncated>
		<difficult>0</difficult>
		<bndbox>
			<xmin>916</xmin>
			<ymin>81</ymin>
			<xmax>929</xmax>
			<ymax>95</ymax>
		</bndbox>
	</object>
	
	<object>
		<name>Pedestrian</name>
		<pose>Unspecified</pose>
		<truncated>0</truncated>
		<difficult>0</difficult>
		<bndbox>
			<xmin>1041</xmin>
			<ymin>50</ymin>
			<xmax>1050</xmax>
			<ymax>71</ymax>
		</bndbox>
	</object>
	
	<object>
		<name>Pedestrian</name>
		<pose>Unspecified</pose>
		<truncated>0</truncated>
		<difficult>0</difficult>
		<bndbox>
			<xmin>1048</xmin>
			<ymin>50</ymin>
			<xmax>1059</xmax>
			<ymax>75</ymax>
		</bndbox>
	</object>
	
	<object>
		<name>People</name>
		<pose>Unspecified</pose>
		<truncated>0</truncated>
		<difficult>0</difficult>
		<bndbox>
			<xmin>859</xmin>
			<ymin>124</ymin>
			<xmax>871</xmax>
			<ymax>148</ymax>
		</bndbox>
	</object>
	
	<object>
		<name>People</name>
		<pose>Unspecified</pose>
		<truncated>0</truncated>
		<difficult>0</difficult>
		<bndbox>
			<xmin>860</xmin>
			<ymin>77</ymin>
			<xmax>868</xmax>
			<ymax>92</ymax>
		</bndbox>
	</object>
	
	<object>
		<name>People</name>
		<pose>Unspecified</pose>
		<truncated>0</truncated>
		<difficult>0</difficult>
		<bndbox>
			<xmin>643</xmin>
			<ymin>562</ymin>
			<xmax>659</xmax>
			<ymax>581</ymax>
		</bndbox>
	</object>
	
	<object>
		<name>People</name>
		<pose>Unspecified</pose>
		<truncated>0</truncated>
		<difficult>0</difficult>
		<bndbox>
			<xmin>636</xmin>
			<ymin>722</ymin>
			<xmax>659</xmax>
			<ymax>743</ymax>
		</bndbox>
	</object>
	
	<object>
		<name>People</name>
		<pose>Unspecified</pose>
		<truncated>0</truncated>
		<difficult>0</difficult>
		<bndbox>
			<xmin>642</xmin>
			<ymin>714</ymin>
			<xmax>654</xmax>
			<ymax>732</ymax>
		</bndbox>
	</object>
	
	<object>
		<name>Pedestrian</name>
		<pose>Unspecified</pose>
		<truncated>0</truncated>
		<difficult>0</difficult>
		<bndbox>
			<xmin>1004</xmin>
			<ymin>31</ymin>
			<xmax>1013</xmax>
			<ymax>55</ymax>
		</bndbox>
	</object>
	
	<object>
		<name>People</name>
		<pose>Unspecified</pose>
		<truncated>0</truncated>
		<difficult>0</difficult>
		<bndbox>
			<xmin>999</xmin>
			<ymin>26</ymin>
			<xmax>1009</xmax>
			<ymax>39</ymax>
		</bndbox>
	</object>
	</annotation>