
<annotation>
	<folder>annotations</folder>
	<filename>9999951_00000_d_0000196.jpg</filename>
	<path>/content/datasets/VisDrone/VisDrone2019-DET-train/images/9999951_00000_d_0000196.jpg</path>
	<source>
		<database>Unknown</database>
	</source>
	<size>
		<width>788</width>
		<height>1400</height>
		<depth>3</depth>
	</size>
	<segmented>0</segmented>
	<object>
		<name>Car</name>
		<pose>Unspecified</pose>
		<truncated>0</truncated>
		<difficult>0</difficult>
		<bndbox>
			<xmin>545</xmin>
			<ymin>390</ymin>
			<xmax>714</xmax>
			<ymax>465</ymax>
		</bndbox>
	</object>
	
	<object>
		<name>Car</name>
		<pose>Unspecified</pose>
		<truncated>0</truncated>
		<difficult>0</difficult>
		<bndbox>
			<xmin>746</xmin>
			<ymin>381</ymin>
			<xmax>897</xmax>
			<ymax>457</ymax>
		</bndbox>
	</object>
	
	<object>
		<name>Car</name>
		<pose>Unspecified</pose>
		<truncated>0</truncated>
		<difficult>0</difficult>
		<bndbox>
			<xmin>977</xmin>
			<ymin>365</ymin>
			<xmax>1112</xmax>
			<ymax>442</ymax>
		</bndbox>
	</object>
	
	<object>
		<name>Car</name>
		<pose>Unspecified</pose>
		<truncated>0</truncated>
		<difficult>0</difficult>
		<bndbox>
			<xmin>1126</xmin>
			<ymin>361</ymin>
			<xmax>1292</xmax>
			<ymax>435</ymax>
		</bndbox>
	</object>
	
	<object>
		<name>Car</name>
		<pose>Unspecified</pose>
		<truncated>0</truncated>
		<difficult>0</difficult>
		<bndbox>
			<xmin>1191</xmin>
			<ymin>520</ymin>
			<xmax>1347</xmax>
			<ymax>602</ymax>
		</bndbox>
	</object>
	
	<object>
		<name>Car</name>
		<pose>Unspecified</pose>
		<truncated>0</truncated>
		<difficult>0</difficult>
		<bndbox>
			<xmin>1151</xmin>
			<ymin>285</ymin>
			<xmax>1300</xmax>
			<ymax>362</ymax>
		</bndbox>
	</object>
	
	<object>
		<name>Car</name>
		<pose>Unspecified</pose>
		<truncated>0</truncated>
		<difficult>0</difficult>
		<bndbox>
			<xmin>439</xmin>
			<ymin>43</ymin>
			<xmax>643</xmax>
			<ymax>144</ymax>
		</bndbox>
	</object>
	
	<object>
		<name>Truck</name>
		<pose>Unspecified</pose>
		<truncated>0</truncated>
		<difficult>0</difficult>
		<bndbox>
			<xmin>0</xmin>
			<ymin>136</ymin>
			<xmax>216</xmax>
			<ymax>327</ymax>
		</bndbox>
	</object>
	</annotation>