
<annotation>
	<folder>annotations</folder>
	<filename>9999965_00000_d_0000071.jpg</filename>
	<path>/content/datasets/VisDrone/VisDrone2019-DET-train/images/9999965_00000_d_0000071.jpg</path>
	<source>
		<database>Unknown</database>
	</source>
	<size>
		<width>788</width>
		<height>1400</height>
		<depth>3</depth>
	</size>
	<segmented>0</segmented>
	<object>
		<name>Car</name>
		<pose>Unspecified</pose>
		<truncated>0</truncated>
		<difficult>0</difficult>
		<bndbox>
			<xmin>541</xmin>
			<ymin>414</ymin>
			<xmax>596</xmax>
			<ymax>464</ymax>
		</bndbox>
	</object>
	
	<object>
		<name>Car</name>
		<pose>Unspecified</pose>
		<truncated>0</truncated>
		<difficult>0</difficult>
		<bndbox>
			<xmin>675</xmin>
			<ymin>399</ymin>
			<xmax>744</xmax>
			<ymax>457</ymax>
		</bndbox>
	</object>
	
	<object>
		<name>Car</name>
		<pose>Unspecified</pose>
		<truncated>0</truncated>
		<difficult>0</difficult>
		<bndbox>
			<xmin>736</xmin>
			<ymin>389</ymin>
			<xmax>805</xmax>
			<ymax>448</ymax>
		</bndbox>
	</object>
	
	<object>
		<name>Car</name>
		<pose>Unspecified</pose>
		<truncated>0</truncated>
		<difficult>0</difficult>
		<bndbox>
			<xmin>876</xmin>
			<ymin>378</ymin>
			<xmax>933</xmax>
			<ymax>439</ymax>
		</bndbox>
	</object>
	
	<object>
		<name>Car</name>
		<pose>Unspecified</pose>
		<truncated>0</truncated>
		<difficult>0</difficult>
		<bndbox>
			<xmin>1090</xmin>
			<ymin>402</ymin>
			<xmax>1159</xmax>
			<ymax>458</ymax>
		</bndbox>
	</object>
	
	<object>
		<name>Car</name>
		<pose>Unspecified</pose>
		<truncated>0</truncated>
		<difficult>0</difficult>
		<bndbox>
			<xmin>979</xmin>
			<ymin>404</ymin>
			<xmax>1058</xmax>
			<ymax>447</ymax>
		</bndbox>
	</object>
	
	<object>
		<name>Car</name>
		<pose>Unspecified</pose>
		<truncated>0</truncated>
		<difficult>0</difficult>
		<bndbox>
			<xmin>1199</xmin>
			<ymin>389</ymin>
			<xmax>1285</xmax>
			<ymax>424</ymax>
		</bndbox>
	</object>
	
	<object>
		<name>Car</name>
		<pose>Unspecified</pose>
		<truncated>0</truncated>
		<difficult>0</difficult>
		<bndbox>
			<xmin>1300</xmin>
			<ymin>383</ymin>
			<xmax>1385</xmax>
			<ymax>422</ymax>
		</bndbox>
	</object>
	
	<object>
		<name>Car</name>
		<pose>Unspecified</pose>
		<truncated>0</truncated>
		<difficult>0</difficult>
		<bndbox>
			<xmin>1289</xmin>
			<ymin>168</ymin>
			<xmax>1326</xmax>
			<ymax>215</ymax>
		</bndbox>
	</object>
	
	<object>
		<name>Car</name>
		<pose>Unspecified</pose>
		<truncated>0</truncated>
		<difficult>0</difficult>
		<bndbox>
			<xmin>1264</xmin>
			<ymin>101</ymin>
			<xmax>1310</xmax>
			<ymax>145</ymax>
		</bndbox>
	</object>
	
	<object>
		<name>Car</name>
		<pose>Unspecified</pose>
		<truncated>0</truncated>
		<difficult>0</difficult>
		<bndbox>
			<xmin>1245</xmin>
			<ymin>68</ymin>
			<xmax>1280</xmax>
			<ymax>111</ymax>
		</bndbox>
	</object>
	
	<object>
		<name>Truck</name>
		<pose>Unspecified</pose>
		<truncated>0</truncated>
		<difficult>0</difficult>
		<bndbox>
			<xmin>1225</xmin>
			<ymin>3</ymin>
			<xmax>1268</xmax>
			<ymax>73</ymax>
		</bndbox>
	</object>
	
	<object>
		<name>Van</name>
		<pose>Unspecified</pose>
		<truncated>0</truncated>
		<difficult>0</difficult>
		<bndbox>
			<xmin>1330</xmin>
			<ymin>263</ymin>
			<xmax>1371</xmax>
			<ymax>322</ymax>
		</bndbox>
	</object>
	
	<object>
		<name>Van</name>
		<pose>Unspecified</pose>
		<truncated>0</truncated>
		<difficult>0</difficult>
		<bndbox>
			<xmin>803</xmin>
			<ymin>377</ymin>
			<xmax>879</xmax>
			<ymax>444</ymax>
		</bndbox>
	</object>
	
	<object>
		<name>Van</name>
		<pose>Unspecified</pose>
		<truncated>0</truncated>
		<difficult>0</difficult>
		<bndbox>
			<xmin>466</xmin>
			<ymin>405</ymin>
			<xmax>535</xmax>
			<ymax>464</ymax>
		</bndbox>
	</object>
	
	<object>
		<name>Car</name>
		<pose>Unspecified</pose>
		<truncated>0</truncated>
		<difficult>0</difficult>
		<bndbox>
			<xmin>413</xmin>
			<ymin>413</ymin>
			<xmax>482</xmax>
			<ymax>478</ymax>
		</bndbox>
	</object>
	
	<object>
		<name>Car</name>
		<pose>Unspecified</pose>
		<truncated>0</truncated>
		<difficult>0</difficult>
		<bndbox>
			<xmin>334</xmin>
			<ymin>431</ymin>
			<xmax>402</xmax>
			<ymax>493</ymax>
		</bndbox>
	</object>
	
	<object>
		<name>Pedestrian</name>
		<pose>Unspecified</pose>
		<truncated>0</truncated>
		<difficult>0</difficult>
		<bndbox>
			<xmin>330</xmin>
			<ymin>524</ymin>
			<xmax>349</xmax>
			<ymax>550</ymax>
		</bndbox>
	</object>
	
	<object>
		<name>Pedestrian</name>
		<pose>Unspecified</pose>
		<truncated>0</truncated>
		<difficult>0</difficult>
		<bndbox>
			<xmin>840</xmin>
			<ymin>456</ymin>
			<xmax>854</xmax>
			<ymax>478</ymax>
		</bndbox>
	</object>
	
	<object>
		<name>Pedestrian</name>
		<pose>Unspecified</pose>
		<truncated>0</truncated>
		<difficult>0</difficult>
		<bndbox>
			<xmin>884</xmin>
			<ymin>459</ymin>
			<xmax>893</xmax>
			<ymax>483</ymax>
		</bndbox>
	</object>
	
	<object>
		<name>Pedestrian</name>
		<pose>Unspecified</pose>
		<truncated>0</truncated>
		<difficult>0</difficult>
		<bndbox>
			<xmin>852</xmin>
			<ymin>444</ymin>
			<xmax>866</xmax>
			<ymax>467</ymax>
		</bndbox>
	</object>
	</annotation>