
<annotation>
	<folder>annotations</folder>
	<filename>9999942_00000_d_0000038.jpg</filename>
	<path>/content/datasets/VisDrone/VisDrone2019-DET-train/images/9999942_00000_d_0000038.jpg</path>
	<source>
		<database>Unknown</database>
	</source>
	<size>
		<width>1050</width>
		<height>1400</height>
		<depth>3</depth>
	</size>
	<segmented>0</segmented>
	<object>
		<name>Car</name>
		<pose>Unspecified</pose>
		<truncated>0</truncated>
		<difficult>0</difficult>
		<bndbox>
			<xmin>162</xmin>
			<ymin>693</ymin>
			<xmax>254</xmax>
			<ymax>833</ymax>
		</bndbox>
	</object>
	
	<object>
		<name>Car</name>
		<pose>Unspecified</pose>
		<truncated>0</truncated>
		<difficult>0</difficult>
		<bndbox>
			<xmin>67</xmin>
			<ymin>641</ymin>
			<xmax>176</xmax>
			<ymax>814</ymax>
		</bndbox>
	</object>
	
	<object>
		<name>Car</name>
		<pose>Unspecified</pose>
		<truncated>0</truncated>
		<difficult>0</difficult>
		<bndbox>
			<xmin>117</xmin>
			<ymin>494</ymin>
			<xmax>214</xmax>
			<ymax>637</ymax>
		</bndbox>
	</object>
	
	<object>
		<name>Pedestrian</name>
		<pose>Unspecified</pose>
		<truncated>0</truncated>
		<difficult>0</difficult>
		<bndbox>
			<xmin>223</xmin>
			<ymin>562</ymin>
			<xmax>255</xmax>
			<ymax>602</ymax>
		</bndbox>
	</object>
	
	<object>
		<name>Pedestrian</name>
		<pose>Unspecified</pose>
		<truncated>0</truncated>
		<difficult>0</difficult>
		<bndbox>
			<xmin>755</xmin>
			<ymin>498</ymin>
			<xmax>778</xmax>
			<ymax>536</ymax>
		</bndbox>
	</object>
	
	<object>
		<name>Pedestrian</name>
		<pose>Unspecified</pose>
		<truncated>0</truncated>
		<difficult>0</difficult>
		<bndbox>
			<xmin>771</xmin>
			<ymin>464</ymin>
			<xmax>791</xmax>
			<ymax>499</ymax>
		</bndbox>
	</object>
	
	<object>
		<name>Awning-tricycle</name>
		<pose>Unspecified</pose>
		<truncated>0</truncated>
		<difficult>0</difficult>
		<bndbox>
			<xmin>836</xmin>
			<ymin>485</ymin>
			<xmax>880</xmax>
			<ymax>573</ymax>
		</bndbox>
	</object>
	
	<object>
		<name>Van</name>
		<pose>Unspecified</pose>
		<truncated>0</truncated>
		<difficult>0</difficult>
		<bndbox>
			<xmin>600</xmin>
			<ymin>814</ymin>
			<xmax>678</xmax>
			<ymax>982</ymax>
		</bndbox>
	</object>
	
	<object>
		<name>Van</name>
		<pose>Unspecified</pose>
		<truncated>0</truncated>
		<difficult>0</difficult>
		<bndbox>
			<xmin>604</xmin>
			<ymin>556</ymin>
			<xmax>677</xmax>
			<ymax>703</ymax>
		</bndbox>
	</object>
	
	<object>
		<name>Car</name>
		<pose>Unspecified</pose>
		<truncated>0</truncated>
		<difficult>0</difficult>
		<bndbox>
			<xmin>601</xmin>
			<ymin>315</ymin>
			<xmax>664</xmax>
			<ymax>433</ymax>
		</bndbox>
	</object>
	
	<object>
		<name>Car</name>
		<pose>Unspecified</pose>
		<truncated>0</truncated>
		<difficult>0</difficult>
		<bndbox>
			<xmin>613</xmin>
			<ymin>203</ymin>
			<xmax>672</xmax>
			<ymax>303</ymax>
		</bndbox>
	</object>
	
	<object>
		<name>Car</name>
		<pose>Unspecified</pose>
		<truncated>0</truncated>
		<difficult>0</difficult>
		<bndbox>
			<xmin>540</xmin>
			<ymin>211</ymin>
			<xmax>596</xmax>
			<ymax>304</ymax>
		</bndbox>
	</object>
	
	<object>
		<name>Car</name>
		<pose>Unspecified</pose>
		<truncated>0</truncated>
		<difficult>0</difficult>
		<bndbox>
			<xmin>590</xmin>
			<ymin>111</ymin>
			<xmax>658</xmax>
			<ymax>186</ymax>
		</bndbox>
	</object>
	
	<object>
		<name>People</name>
		<pose>Unspecified</pose>
		<truncated>0</truncated>
		<difficult>0</difficult>
		<bndbox>
			<xmin>511</xmin>
			<ymin>645</ymin>
			<xmax>535</xmax>
			<ymax>676</ymax>
		</bndbox>
	</object>
	
	<object>
		<name>Motor</name>
		<pose>Unspecified</pose>
		<truncated>0</truncated>
		<difficult>0</difficult>
		<bndbox>
			<xmin>513</xmin>
			<ymin>636</ymin>
			<xmax>534</xmax>
			<ymax>698</ymax>
		</bndbox>
	</object>
	
	<object>
		<name>Motor</name>
		<pose>Unspecified</pose>
		<truncated>0</truncated>
		<difficult>0</difficult>
		<bndbox>
			<xmin>826</xmin>
			<ymin>623</ymin>
			<xmax>885</xmax>
			<ymax>671</ymax>
		</bndbox>
	</object>
	
	<object>
		<name>Motor</name>
		<pose>Unspecified</pose>
		<truncated>0</truncated>
		<difficult>0</difficult>
		<bndbox>
			<xmin>782</xmin>
			<ymin>548</ymin>
			<xmax>839</xmax>
			<ymax>597</ymax>
		</bndbox>
	</object>
	
	<object>
		<name>Pedestrian</name>
		<pose>Unspecified</pose>
		<truncated>0</truncated>
		<difficult>0</difficult>
		<bndbox>
			<xmin>888</xmin>
			<ymin>793</ymin>
			<xmax>911</xmax>
			<ymax>827</ymax>
		</bndbox>
	</object>
	
	<object>
		<name>Pedestrian</name>
		<pose>Unspecified</pose>
		<truncated>0</truncated>
		<difficult>0</difficult>
		<bndbox>
			<xmin>729</xmin>
			<ymin>506</ymin>
			<xmax>750</xmax>
			<ymax>545</ymax>
		</bndbox>
	</object>
	
	<object>
		<name>People</name>
		<pose>Unspecified</pose>
		<truncated>0</truncated>
		<difficult>0</difficult>
		<bndbox>
			<xmin>513</xmin>
			<ymin>179</ymin>
			<xmax>533</xmax>
			<ymax>221</ymax>
		</bndbox>
	</object>
	
	<object>
		<name>Bicycle</name>
		<pose>Unspecified</pose>
		<truncated>0</truncated>
		<difficult>0</difficult>
		<bndbox>
			<xmin>517</xmin>
			<ymin>190</ymin>
			<xmax>532</xmax>
			<ymax>231</ymax>
		</bndbox>
	</object>
	
	<object>
		<name>Bicycle</name>
		<pose>Unspecified</pose>
		<truncated>0</truncated>
		<difficult>0</difficult>
		<bndbox>
			<xmin>751</xmin>
			<ymin>88</ymin>
			<xmax>775</xmax>
			<ymax>120</ymax>
		</bndbox>
	</object>
	
	<object>
		<name>Motor</name>
		<pose>Unspecified</pose>
		<truncated>0</truncated>
		<difficult>0</difficult>
		<bndbox>
			<xmin>763</xmin>
			<ymin>63</ymin>
			<xmax>782</xmax>
			<ymax>98</ymax>
		</bndbox>
	</object>
	
	<object>
		<name>Pedestrian</name>
		<pose>Unspecified</pose>
		<truncated>0</truncated>
		<difficult>0</difficult>
		<bndbox>
			<xmin>303</xmin>
			<ymin>114</ymin>
			<xmax>327</xmax>
			<ymax>154</ymax>
		</bndbox>
	</object>
	
	<object>
		<name>Car</name>
		<pose>Unspecified</pose>
		<truncated>0</truncated>
		<difficult>0</difficult>
		<bndbox>
			<xmin>298</xmin>
			<ymin>0</ymin>
			<xmax>402</xmax>
			<ymax>28</ymax>
		</bndbox>
	</object>
	</annotation>