
<annotation>
	<folder>annotations</folder>
	<filename>9999942_00000_d_0000058.jpg</filename>
	<path>/content/datasets/VisDrone/VisDrone2019-DET-train/images/9999942_00000_d_0000058.jpg</path>
	<source>
		<database>Unknown</database>
	</source>
	<size>
		<width>1050</width>
		<height>1400</height>
		<depth>3</depth>
	</size>
	<segmented>0</segmented>
	<object>
		<name>Van</name>
		<pose>Unspecified</pose>
		<truncated>0</truncated>
		<difficult>0</difficult>
		<bndbox>
			<xmin>69</xmin>
			<ymin>665</ymin>
			<xmax>211</xmax>
			<ymax>734</ymax>
		</bndbox>
	</object>
	
	<object>
		<name>Van</name>
		<pose>Unspecified</pose>
		<truncated>0</truncated>
		<difficult>0</difficult>
		<bndbox>
			<xmin>363</xmin>
			<ymin>714</ymin>
			<xmax>543</xmax>
			<ymax>799</ymax>
		</bndbox>
	</object>
	
	<object>
		<name>Awning-tricycle</name>
		<pose>Unspecified</pose>
		<truncated>0</truncated>
		<difficult>0</difficult>
		<bndbox>
			<xmin>237</xmin>
			<ymin>662</ymin>
			<xmax>277</xmax>
			<ymax>691</ymax>
		</bndbox>
	</object>
	
	<object>
		<name>Awning-tricycle</name>
		<pose>Unspecified</pose>
		<truncated>0</truncated>
		<difficult>0</difficult>
		<bndbox>
			<xmin>501</xmin>
			<ymin>648</ymin>
			<xmax>554</xmax>
			<ymax>673</ymax>
		</bndbox>
	</object>
	
	<object>
		<name>Awning-tricycle</name>
		<pose>Unspecified</pose>
		<truncated>0</truncated>
		<difficult>0</difficult>
		<bndbox>
			<xmin>417</xmin>
			<ymin>358</ymin>
			<xmax>439</xmax>
			<ymax>385</ymax>
		</bndbox>
	</object>
	
	<object>
		<name>Awning-tricycle</name>
		<pose>Unspecified</pose>
		<truncated>0</truncated>
		<difficult>0</difficult>
		<bndbox>
			<xmin>439</xmin>
			<ymin>361</ymin>
			<xmax>479</xmax>
			<ymax>386</ymax>
		</bndbox>
	</object>
	
	<object>
		<name>Pedestrian</name>
		<pose>Unspecified</pose>
		<truncated>0</truncated>
		<difficult>0</difficult>
		<bndbox>
			<xmin>438</xmin>
			<ymin>447</ymin>
			<xmax>461</xmax>
			<ymax>479</ymax>
		</bndbox>
	</object>
	
	<object>
		<name>Car</name>
		<pose>Unspecified</pose>
		<truncated>0</truncated>
		<difficult>0</difficult>
		<bndbox>
			<xmin>410</xmin>
			<ymin>495</ymin>
			<xmax>550</xmax>
			<ymax>554</ymax>
		</bndbox>
	</object>
	
	<object>
		<name>Awning-tricycle</name>
		<pose>Unspecified</pose>
		<truncated>0</truncated>
		<difficult>0</difficult>
		<bndbox>
			<xmin>398</xmin>
			<ymin>380</ymin>
			<xmax>464</xmax>
			<ymax>437</ymax>
		</bndbox>
	</object>
	
	<object>
		<name>Pedestrian</name>
		<pose>Unspecified</pose>
		<truncated>0</truncated>
		<difficult>0</difficult>
		<bndbox>
			<xmin>977</xmin>
			<ymin>284</ymin>
			<xmax>993</xmax>
			<ymax>318</ymax>
		</bndbox>
	</object>
	
	<object>
		<name>Pedestrian</name>
		<pose>Unspecified</pose>
		<truncated>0</truncated>
		<difficult>0</difficult>
		<bndbox>
			<xmin>1007</xmin>
			<ymin>394</ymin>
			<xmax>1022</xmax>
			<ymax>430</ymax>
		</bndbox>
	</object>
	
	<object>
		<name>Car</name>
		<pose>Unspecified</pose>
		<truncated>0</truncated>
		<difficult>0</difficult>
		<bndbox>
			<xmin>1142</xmin>
			<ymin>489</ymin>
			<xmax>1263</xmax>
			<ymax>561</ymax>
		</bndbox>
	</object>
	
	<object>
		<name>Car</name>
		<pose>Unspecified</pose>
		<truncated>0</truncated>
		<difficult>0</difficult>
		<bndbox>
			<xmin>1197</xmin>
			<ymin>612</ymin>
			<xmax>1334</xmax>
			<ymax>691</ymax>
		</bndbox>
	</object>
	
	<object>
		<name>Car</name>
		<pose>Unspecified</pose>
		<truncated>0</truncated>
		<difficult>0</difficult>
		<bndbox>
			<xmin>1117</xmin>
			<ymin>385</ymin>
			<xmax>1191</xmax>
			<ymax>454</ymax>
		</bndbox>
	</object>
	
	<object>
		<name>Car</name>
		<pose>Unspecified</pose>
		<truncated>0</truncated>
		<difficult>0</difficult>
		<bndbox>
			<xmin>985</xmin>
			<ymin>158</ymin>
			<xmax>1059</xmax>
			<ymax>204</ymax>
		</bndbox>
	</object>
	
	<object>
		<name>Pedestrian</name>
		<pose>Unspecified</pose>
		<truncated>0</truncated>
		<difficult>0</difficult>
		<bndbox>
			<xmin>954</xmin>
			<ymin>114</ymin>
			<xmax>966</xmax>
			<ymax>144</ymax>
		</bndbox>
	</object>
	
	<object>
		<name>Car</name>
		<pose>Unspecified</pose>
		<truncated>0</truncated>
		<difficult>0</difficult>
		<bndbox>
			<xmin>714</xmin>
			<ymin>38</ymin>
			<xmax>742</xmax>
			<ymax>79</ymax>
		</bndbox>
	</object>
	
	<object>
		<name>Car</name>
		<pose>Unspecified</pose>
		<truncated>0</truncated>
		<difficult>0</difficult>
		<bndbox>
			<xmin>1079</xmin>
			<ymin>299</ymin>
			<xmax>1134</xmax>
			<ymax>373</ymax>
		</bndbox>
	</object>
	
	<object>
		<name>Car</name>
		<pose>Unspecified</pose>
		<truncated>0</truncated>
		<difficult>0</difficult>
		<bndbox>
			<xmin>1225</xmin>
			<ymin>805</ymin>
			<xmax>1356</xmax>
			<ymax>962</ymax>
		</bndbox>
	</object>
	
	<object>
		<name>Bicycle</name>
		<pose>Unspecified</pose>
		<truncated>0</truncated>
		<difficult>0</difficult>
		<bndbox>
			<xmin>1306</xmin>
			<ymin>673</ymin>
			<xmax>1351</xmax>
			<ymax>699</ymax>
		</bndbox>
	</object>
	
	<object>
		<name>Bicycle</name>
		<pose>Unspecified</pose>
		<truncated>0</truncated>
		<difficult>0</difficult>
		<bndbox>
			<xmin>1332</xmin>
			<ymin>625</ymin>
			<xmax>1354</xmax>
			<ymax>666</ymax>
		</bndbox>
	</object>
	
	<object>
		<name>Bicycle</name>
		<pose>Unspecified</pose>
		<truncated>0</truncated>
		<difficult>0</difficult>
		<bndbox>
			<xmin>1339</xmin>
			<ymin>621</ymin>
			<xmax>1362</xmax>
			<ymax>665</ymax>
		</bndbox>
	</object>
	
	<object>
		<name>Car</name>
		<pose>Unspecified</pose>
		<truncated>0</truncated>
		<difficult>0</difficult>
		<bndbox>
			<xmin>664</xmin>
			<ymin>28</ymin>
			<xmax>694</xmax>
			<ymax>64</ymax>
		</bndbox>
	</object>
	</annotation>