
<annotation>
	<folder>annotations</folder>
	<filename>9999953_00000_d_0000141.jpg</filename>
	<path>/content/datasets/VisDrone/VisDrone2019-DET-train/images/9999953_00000_d_0000141.jpg</path>
	<source>
		<database>Unknown</database>
	</source>
	<size>
		<width>788</width>
		<height>1400</height>
		<depth>3</depth>
	</size>
	<segmented>0</segmented>
	<object>
		<name>Pedestrian</name>
		<pose>Unspecified</pose>
		<truncated>0</truncated>
		<difficult>0</difficult>
		<bndbox>
			<xmin>906</xmin>
			<ymin>693</ymin>
			<xmax>922</xmax>
			<ymax>704</ymax>
		</bndbox>
	</object>
	
	<object>
		<name>Pedestrian</name>
		<pose>Unspecified</pose>
		<truncated>0</truncated>
		<difficult>0</difficult>
		<bndbox>
			<xmin>936</xmin>
			<ymin>666</ymin>
			<xmax>948</xmax>
			<ymax>683</ymax>
		</bndbox>
	</object>
	
	<object>
		<name>Pedestrian</name>
		<pose>Unspecified</pose>
		<truncated>0</truncated>
		<difficult>0</difficult>
		<bndbox>
			<xmin>860</xmin>
			<ymin>675</ymin>
			<xmax>876</xmax>
			<ymax>689</ymax>
		</bndbox>
	</object>
	
	<object>
		<name>Pedestrian</name>
		<pose>Unspecified</pose>
		<truncated>0</truncated>
		<difficult>0</difficult>
		<bndbox>
			<xmin>956</xmin>
			<ymin>696</ymin>
			<xmax>970</xmax>
			<ymax>709</ymax>
		</bndbox>
	</object>
	
	<object>
		<name>Car</name>
		<pose>Unspecified</pose>
		<truncated>0</truncated>
		<difficult>0</difficult>
		<bndbox>
			<xmin>779</xmin>
			<ymin>651</ymin>
			<xmax>832</xmax>
			<ymax>686</ymax>
		</bndbox>
	</object>
	
	<object>
		<name>Car</name>
		<pose>Unspecified</pose>
		<truncated>0</truncated>
		<difficult>0</difficult>
		<bndbox>
			<xmin>765</xmin>
			<ymin>618</ymin>
			<xmax>811</xmax>
			<ymax>649</ymax>
		</bndbox>
	</object>
	
	<object>
		<name>Car</name>
		<pose>Unspecified</pose>
		<truncated>0</truncated>
		<difficult>0</difficult>
		<bndbox>
			<xmin>688</xmin>
			<ymin>641</ymin>
			<xmax>741</xmax>
			<ymax>679</ymax>
		</bndbox>
	</object>
	
	<object>
		<name>Truck</name>
		<pose>Unspecified</pose>
		<truncated>0</truncated>
		<difficult>0</difficult>
		<bndbox>
			<xmin>688</xmin>
			<ymin>682</ymin>
			<xmax>748</xmax>
			<ymax>721</ymax>
		</bndbox>
	</object>
	
	<object>
		<name>Van</name>
		<pose>Unspecified</pose>
		<truncated>0</truncated>
		<difficult>0</difficult>
		<bndbox>
			<xmin>602</xmin>
			<ymin>712</ymin>
			<xmax>663</xmax>
			<ymax>752</ymax>
		</bndbox>
	</object>
	
	<object>
		<name>Truck</name>
		<pose>Unspecified</pose>
		<truncated>0</truncated>
		<difficult>0</difficult>
		<bndbox>
			<xmin>534</xmin>
			<ymin>662</ymin>
			<xmax>667</xmax>
			<ymax>733</ymax>
		</bndbox>
	</object>
	
	<object>
		<name>Car</name>
		<pose>Unspecified</pose>
		<truncated>0</truncated>
		<difficult>0</difficult>
		<bndbox>
			<xmin>521</xmin>
			<ymin>738</ymin>
			<xmax>581</xmax>
			<ymax>775</ymax>
		</bndbox>
	</object>
	
	<object>
		<name>Car</name>
		<pose>Unspecified</pose>
		<truncated>0</truncated>
		<difficult>0</difficult>
		<bndbox>
			<xmin>425</xmin>
			<ymin>728</ymin>
			<xmax>488</xmax>
			<ymax>768</ymax>
		</bndbox>
	</object>
	
	<object>
		<name>Car</name>
		<pose>Unspecified</pose>
		<truncated>0</truncated>
		<difficult>0</difficult>
		<bndbox>
			<xmin>350</xmin>
			<ymin>763</ymin>
			<xmax>413</xmax>
			<ymax>787</ymax>
		</bndbox>
	</object>
	
	<object>
		<name>Bus</name>
		<pose>Unspecified</pose>
		<truncated>0</truncated>
		<difficult>0</difficult>
		<bndbox>
			<xmin>1015</xmin>
			<ymin>183</ymin>
			<xmax>1081</xmax>
			<ymax>256</ymax>
		</bndbox>
	</object>
	</annotation>